[
    {
        "key": "dbln",
        "value": "%7B%2261586118752384%22%3A%22FKB6cyNR%22%7D",
        "domain": "facebook.com",
        "path": "/login/device-based/",
        "hostOnly": false,
        "creation": "2026-01-16T20:29:09.722Z",
        "lastAccessed": "2026-01-16T20:29:09.723Z"
    },
    {
        "key": "datr",
        "value": "gpVqablth7IogpUo-e5dNrmJ",
        "domain": "facebook.com",
        "path": "/",
        "hostOnly": false,
        "creation": "2026-01-16T20:29:09.723Z",
        "lastAccessed": "2026-01-16T20:29:09.723Z"
    },
    {
        "key": "ps_l",
        "value": "1",
        "domain": "facebook.com",
        "path": "/",
        "hostOnly": false,
        "creation": "2026-01-16T20:29:09.723Z",
        "lastAccessed": "2026-01-16T20:29:09.723Z"
    },
    {
        "key": "ps_n",
        "value": "1",
        "domain": "facebook.com",
        "path": "/",
        "hostOnly": false,
        "creation": "2026-01-16T20:29:09.723Z",
        "lastAccessed": "2026-01-16T20:29:09.723Z"
    },
    {
        "key": "sb",
        "value": "g5VqaX9CArVSVrMupIPHHRTT",
        "domain": "facebook.com",
        "path": "/",
        "hostOnly": false,
        "creation": "2026-01-16T20:29:09.723Z",
        "lastAccessed": "2026-01-16T20:29:09.723Z"
    },
    {
        "key": "locale",
        "value": "en_US",
        "domain": "facebook.com",
        "path": "/",
        "hostOnly": false,
        "creation": "2026-01-16T20:29:09.723Z",
        "lastAccessed": "2026-01-16T20:29:09.723Z"
    },
    {
        "key": "pas",
        "value": "61586118752384%3Ad0z7Gw7d46",
        "domain": "facebook.com",
        "path": "/",
        "hostOnly": false,
        "creation": "2026-01-16T20:29:09.723Z",
        "lastAccessed": "2026-01-16T20:29:09.723Z"
    },
    {
        "key": "vpd",
        "value": "v1%3B751x412x2.625",
        "domain": "facebook.com",
        "path": "/",
        "hostOnly": false,
        "creation": "2026-01-16T20:29:09.723Z",
        "lastAccessed": "2026-01-16T20:29:09.723Z"
    },
    {
        "key": "m_pixel_ratio",
        "value": "2.625",
        "domain": "facebook.com",
        "path": "/",
        "hostOnly": false,
        "creation": "2026-01-16T20:29:09.723Z",
        "lastAccessed": "2026-01-16T20:29:09.723Z"
    },
    {
        "key": "wd",
        "value": "412x846",
        "domain": "facebook.com",
        "path": "/",
        "hostOnly": false,
        "creation": "2026-01-16T20:29:09.723Z",
        "lastAccessed": "2026-01-16T20:29:09.723Z"
    },
    {
        "key": "wl_cbv",
        "value": "v2%3Bclient_version%3A3055%3Btimestamp%3A1768594649",
        "domain": "facebook.com",
        "path": "/",
        "hostOnly": false,
        "creation": "2026-01-16T20:29:09.723Z",
        "lastAccessed": "2026-01-16T20:29:09.723Z"
    },
    {
        "key": "fr",
        "value": "0HGOtPh1OJDra33iY.AWcmk2Mtc8RWLRhxwguLrD7K2QUyPhNzkLq9wmSdLkBIMKECMAs.BpapWD..AAA.0.0.Bpap93.AWfbj-Ro7SQWoRpLzWzOg4Y37b0",
        "domain": "facebook.com",
        "path": "/",
        "hostOnly": false,
        "creation": "2026-01-16T20:29:09.723Z",
        "lastAccessed": "2026-01-16T20:29:09.723Z"
    }
]
